odoo8_addon_medical_medication_us-8.0.1.0.0.99.dev3-py2.7-nspkg.pth
odoo8_addon_medical_medication_us-8.0.1.0.0.99.dev3.dist-info/DESCRIPTION.rst
odoo8_addon_medical_medication_us-8.0.1.0.0.99.dev3.dist-info/METADATA
odoo8_addon_medical_medication_us-8.0.1.0.0.99.dev3.dist-info/RECORD
odoo8_addon_medical_medication_us-8.0.1.0.0.99.dev3.dist-info/WHEEL
odoo8_addon_medical_medication_us-8.0.1.0.0.99.dev3.dist-info/metadata.json
odoo8_addon_medical_medication_us-8.0.1.0.0.99.dev3.dist-info/namespace_packages.txt
odoo8_addon_medical_medication_us-8.0.1.0.0.99.dev3.dist-info/top_level.txt
odoo_addons/medical_medication_us/README.rst
odoo_addons/medical_medication_us/__init__.py
odoo_addons/medical_medication_us/__openerp__.py
odoo_addons/medical_medication_us/i18n/pt_BR.po
odoo_addons/medical_medication_us/models/__init__.py
odoo_addons/medical_medication_us/models/medical_medicament.py
odoo_addons/medical_medication_us/models/medical_medication_template.py
odoo_addons/medical_medication_us/views/medical_medicament_view.xml
